pytest_hidecaptured.py
pytest_hidecaptured-0.2.2.dist-info/METADATA
pytest_hidecaptured-0.2.2.dist-info/RECORD
pytest_hidecaptured-0.2.2.dist-info/WHEEL
pytest_hidecaptured-0.2.2.dist-info/entry_points.txt
pytest_hidecaptured-0.2.2.dist-info/top_level.txt
