Metadata-Version: 2.1
Name: pytest-hidecaptured
Version: 0.2.2
Summary: Hide captured output
Home-page: https://github.com/codeghar/pytest-hidecaptured
Author: Hamza Sheikh
Author-email: code@codeghar.com
Maintainer: Hamza Sheikh
Maintainer-email: code@codeghar.com
License: MIT
Platform: UNKNOWN
Classifier: Development Status :: 4 - Beta
Classifier: Intended Audience :: Developers
Classifier: Topic :: Software Development :: Testing
Classifier: Programming Language :: Python
Classifier: Programming Language :: Python :: 2
Classifier: Programming Language :: Python :: 2.7
Classifier: Programming Language :: Python :: 3
Classifier: Programming Language :: Python :: 3.6
Classifier: Programming Language :: Python :: Implementation :: CPython
Classifier: Programming Language :: Python :: Implementation :: PyPy
Classifier: Operating System :: OS Independent
Classifier: License :: OSI Approved :: MIT License
Requires-Dist: pytest (>=2.8.5)
